arkana_build_example_pkg/__init__.py
arkana_build_example_pkg/py.typed
arkana_build_tools_example_pkg-0.1.0.dist-info/METADATA
arkana_build_tools_example_pkg-0.1.0.dist-info/WHEEL
arkana_build_tools_example_pkg-0.1.0.dist-info/RECORD
