Metadata-Version: 2.1
Name: arkana-build-tools-example-pkg
Version: 0.1.0
Summary: TBD.
Author: Sivam Pasupathipillai
Author-email: sivam.pasupathipillai@gmail.com
Requires-Python: >=3.11,<3.12
Classifier: Programming Language :: Python :: 3
Classifier: Programming Language :: Python :: 3.11
